async_iamport/__init__.py
async_iamport/client.py
async_iamport-0.2.0.dist-info/METADATA
async_iamport-0.2.0.dist-info/WHEEL
async_iamport-0.2.0.dist-info/LICENSE
async_iamport-0.2.0.dist-info/RECORD
